pae/__init__.py
pae/pae.py
pae-1.0.0.dist-info/METADATA
pae-1.0.0.dist-info/RECORD
pae-1.0.0.dist-info/WHEEL
pae-1.0.0.dist-info/top_level.txt
test/__init__.py
test/test_pae.py
