Metadata-Version: 2.1
Name: pae
Version: 1.0.0
Summary: Pixel Approximate Entropy
Home-page: https://github.com/gryan11/pae
Author: Gabriel Ryan
Author-email: gabriel.ryan@columbia.edu
License: UNKNOWN
Platform: UNKNOWN
Requires-Dist: numpy
